DbtPy.cp37-win_amd64.pyd
DbtPyDbi.py
DbtPy-3.0.5.2.dist-info/LICENSE
DbtPy-3.0.5.2.dist-info/METADATA
DbtPy-3.0.5.2.dist-info/WHEEL
DbtPy-3.0.5.2.dist-info/top_level.txt
DbtPy-3.0.5.2.dist-info/RECORD
