Metadata-Version: 2.1
Name: DbtPy
Version: 3.0.5.2
Summary: GBase 8s native Python driver
Home-page: UNKNOWN
Author: Informix Application Development Team & GBase 8s Support Team
License: Apache License 2.0
Project-URL: Documentation, https://gbasedbt.com/DbtPy/wiki
Project-URL: Source, https://gbasedbt.com/DbtPy
Project-URL: Tracker, https://gbasedbt.com/DbtPy
Keywords: GBase 8s Python Enterprise
Platform: UNKNOWN
Classifier: Development Status :: 5 - Production/Stable
Classifier: Intended Audience :: Developers
Classifier: Topic :: Software Development
Classifier: License :: OSI Approved :: Apache Software License
Classifier: Programming Language :: Python :: 2.7
Classifier: Programming Language :: Python :: 3.4
Classifier: Programming Language :: Python :: 3.5
Classifier: Programming Language :: Python :: 3.6
Classifier: Programming Language :: Python :: 3.7
Classifier: Operating System :: Microsoft :: Windows
Classifier: Operating System :: POSIX
Classifier: Programming Language :: Python :: Implementation :: CPython
Requires-Python: ~=3.4
